kernel_run/__init__.py
kernel_run/_version.py
kernel_run/cli.py
kernel_run/utils/__init__.py
kernel_run/utils/creds.py
kernel_run/utils/jupyter.py
kernel_run/utils/misc.py
kernel_run/utils/network.py
kernel_run-0.0.13.dist-info/METADATA
kernel_run-0.0.13.dist-info/WHEEL
kernel_run-0.0.13.dist-info/entry_points.txt
kernel_run-0.0.13.dist-info/top_level.txt
kernel_run-0.0.13.dist-info/RECORD
