Metadata-Version: 2.1
Name: kernel-run
Version: 0.0.13
Summary: Run any Jupyter notebook on Kaggle kernels instantly
Home-page: https://github.com/swiftace-ai/kernel-run
Author: SwiftAce
Author-email: opensource@swiftace.ai
License: UNKNOWN
Platform: UNKNOWN
Classifier: Programming Language :: Python :: 3
Classifier: License :: OSI Approved :: MIT License
Classifier: Operating System :: OS Independent
Requires-Dist: requests
Requires-Dist: six
